flaxfile/__init__.py
flaxfile/cli.py
flaxfile/config.py
flaxfile/crypto.py
flaxfile/multi_socket_client.py
flaxfile/server.py
flaxfile/sync.py
flaxfile-1.3.0.dist-info/METADATA
flaxfile-1.3.0.dist-info/WHEEL
flaxfile-1.3.0.dist-info/entry_points.txt
flaxfile-1.3.0.dist-info/RECORD
