Metadata-Version: 2.4
Name: flaxfile
Version: 1.3.0
Summary: 高性能文件传输工具 - 基于ZMQ优化的跨网络文件传输系统
Project-URL: Homepage, https://github.com/KenyonY/flaxkv
Project-URL: Documentation, https://github.com/KenyonY/flaxkv/tree/main/flaxfile#flaxfile
Project-URL: Issues, https://github.com/KenyonY/flaxkv/issues
Project-URL: Source, https://github.com/KenyonY/flaxkv/tree/main/flaxfile
Author-email: "K.Y" <beidongjiedeguang@gmail.com>
License: MIT
Keywords: file-transfer,high-performance,network,streaming,zmq
Classifier: Development Status :: 4 - Beta
Classifier: Intended Audience :: Developers
Classifier: License :: OSI Approved :: MIT License
Classifier: Operating System :: OS Independent
Classifier: Programming Language :: Python :: 3
Classifier: Programming Language :: Python :: 3.8
Classifier: Programming Language :: Python :: 3.9
Classifier: Programming Language :: Python :: 3.10
Classifier: Programming Language :: Python :: 3.11
Classifier: Programming Language :: Python :: 3.12
Classifier: Topic :: System :: Networking
Classifier: Topic :: Utilities
Requires-Python: >=3.8
Requires-Dist: aiofiles>=23.0.0
Requires-Dist: fire>=0.5.0
Requires-Dist: loguru>=0.7.0
Requires-Dist: pynacl>=1.5.0
Requires-Dist: pyzmq>=25.0.0
Requires-Dist: questionary>=2.0.0
Requires-Dist: rich>=13.0.0
Requires-Dist: toml>=0.10.0
Requires-Dist: tomli>=2.0.0; python_version < '3.11'
Requires-Dist: xxhash>=3.0.0
